ml4proflow_mods_io-1.1-py3.11-nspkg.pth
ml4proflow_mods/__version__.py
ml4proflow_mods/io/__init__.py
ml4proflow_mods/io/exceptions.py
ml4proflow_mods/io/file_readers.py
ml4proflow_mods/io/file_writers.py
ml4proflow_mods/io/modules.py
ml4proflow_mods_io-1.1.dist-info/LICENSE.txt
ml4proflow_mods_io-1.1.dist-info/METADATA
ml4proflow_mods_io-1.1.dist-info/WHEEL
ml4proflow_mods_io-1.1.dist-info/namespace_packages.txt
ml4proflow_mods_io-1.1.dist-info/top_level.txt
ml4proflow_mods_io-1.1.dist-info/RECORD
