Metadata-Version: 2.1
Name: ml4proflow-mods-io
Version: 1.1
Summary: IO Modules for the Framework
Home-page: https://gitlab.ub.uni-bielefeld.de/ml4proflow/ml4proflow-mods-io
Author: Christian Klarhorst
Author-email: cklarhor@techfak.uni-bielefeld.de
Project-URL: Main framework, https://gitlab.ub.uni-bielefeld.de/ml4proflow/ml4proflow
Classifier: Development Status :: 4 - Beta
Classifier: Intended Audience :: Developers
Classifier: Programming Language :: Python :: 3
Classifier: Topic :: Scientific/Engineering :: Artificial Intelligence
Classifier: License :: OSI Approved :: MIT License
Classifier: Operating System :: OS Independent
Requires-Python: >=3.6
License-File: LICENSE.txt
Requires-Dist: ml4proflow
Requires-Dist: pyarrow
Requires-Dist: tables
Provides-Extra: docs
Requires-Dist: sphinx ; extra == 'docs'
Requires-Dist: sphinx-rtd-theme ; extra == 'docs'
Requires-Dist: recommonmark ; extra == 'docs'
Provides-Extra: tests
Requires-Dist: pytest ; extra == 'tests'
Requires-Dist: pandas-stubs ; extra == 'tests'
Requires-Dist: pytest-html ; extra == 'tests'
Requires-Dist: pytest-cov ; extra == 'tests'
Requires-Dist: flake8 ; extra == 'tests'
Requires-Dist: mypy ; extra == 'tests'
Requires-Dist: jinja2 (==3.0.3) ; extra == 'tests'
